{"author":"Ferdinand Xerbutri","updated":"2025-03-11","created":"2025-03-11","shortname":"Norre Nebel","description":"Ferdinand Xerbutri fietst langs een verlaten Deense militaire spoorweg","realname":"Norre Nebel - Nymindegab","title":"Norre Nebel","intro":"In Denemarken 2015","adventure":"","history":"Baan in 1941 aangelegd door Duitsers.<br>Veel sabotage gedurende 1943<br>Na 1945 bleef lijn open, de duinlijn is in 1945-1946 aangelegd.<br>Alleen militair vervoer en goederen<br>In 1976 overwoog VNJ personenvervoer naar Nymindegab, maar te weinig verwacht verkeer.<br>Spoorweg begin tachtiger jaren gesloten voor verkeer.<br>Heropende in 1984 voor militair verkeer.<br>In 1990 is spoor aan vervanging toe, maar strijdkrachten wilden dat niet financieren.<br>Sinds 2001 spoorfietsen en in de eropvolgende jaren sporadisch gebruik voor historisch materiaal.<br>Spooraansluiting is opgebroken, dus geen treinverkeer meer mogelijk, alleen spoorfietsen."}