{"author":"Ferdinand Xerbutri","updated":"2025-06-10","created":"2025-05-22","shortname":"Scierie B","description":"Ferdinand Xerbutri ontdekt een verlaten -houtzagerij in Breitenwasen","realname":"Scierie Breitenwasen Usine Vapeur","title":"Scierie B","intro":"<p>Kwam ik tegen tijdens vakantie</p>","adventure":"","history":"<p>Waarschijnlijk was hier al lang lang geleden een houtzagerij die gebruik maakte van waterkracht. De fabriek staat al op oude Franse kaarten uit 1866. In het gebouw zelf is veel terug te vinden. Franse luchtfoto's tonen dat het leegstaat sinds 1999.</p>"}