{"author":"Team Xerbutri","updated":"2007-08-05","created":"2007-02-01","shortname":"Fort Walem","description":"TBD","realname":"Fort van Walem","title":"Fort van Walem","intro":"<p>We hebben deze locatie met het team in februari 2007 bezocht. Overal liggen gasmaskers, verder is er veel brand geweest dus weinig te zien helaas.</p>","adventure":"","history":"<p>Dit fort maakt deel uit van de fortenring rond Antwerpen, de nationale redoute van België. Het Fort is in de periode van 1878 tot 1893 gebouwd ter versterking van de stad. Een nieuwe soort artillerie had de binnenste fortenring min of meer overbodig gemaakt. In 1914 werd het Fort voor het eerst gebruikt, met rampzalige gevolgen. Het Duitse geschut kon ongestoord het fort in puin schieten. Het was zwaarder dan het Belgisch geschut en had bovendien een groter bereik. Tijdens het hoogtepunt werd het fort beschoten met zo'n twintig granaten per minuut. Het fort was niet berekend op dit soort vuur. Door een voltreffer in het kruitmagazijn stortte een aantal galerijen in. Meer dan 70 mensen die zich op dat moment in dat deel bevonden werden verzwolgen. Ter gedachtenis aan het heldhaftige verzet werd een monument aangebracht op het fort, een weerstanderskruis. Na de eerste wereldoorlog was het duidelijk dat de fortengordel geen nut had en werd opgeheven. Het Fort van Walem werd hergebruikt door de civiele bescherming. Eind jaren tachtig met het aflopen van de koude oorlog verliest het fort zijn belang en raakt buiten gebruik. Ergens in die tijd wordt er dan een asielzoekerscentrum in gevestigd. In 1992 wordt dit centrum na een grote brand gesloten. Het fort is sindsdien buiten gebruik en heeft te lijden onder vandalisme en brandstichting. Een nieuwe bestemming van het fort vinden wordt moeilijk vanwege de ruim 70 manschappen die onder de gewelven van het fort begraven liggen. Het is onduidelijk wat er met het fort zal gebeuren. </p>"}