{"type":"FeatureCollection","features":[{"type":"Feature","geometry":{"type":"Point","coordinates":[5.08233545313202,51.5602917055715]},"properties":{"Index":0}},{"type":"Feature","geometry":{"type":"Point","coordinates":[5.08204245875411,51.56079405855823]},"properties":{"Index":1}},{"type":"Feature","geometry":{"type":"Point","coordinates":[5.0770738909354,51.56099729902951]},"properties":{"Index":2}},{"type":"Feature","geometry":{"type":"Point","coordinates":[5.0652662289173,51.56285167974798]},"properties":{"Index":3}},{"type":"Feature","geometry":{"type":"Point","coordinates":[5.0539972424231,51.55481164281537]},"properties":{"Index":4}},{"type":"Feature","geometry":{"type":"Point","coordinates":[5.0495493279876,51.55112106793942]},"properties":{"Index":5}},{"type":"Feature","geometry":{"type":"Point","coordinates":[5.03619138583289,51.5403899280027]},"properties":{"Index":6}},{"type":"Feature","geometry":{"type":"Point","coordinates":[5.02935460467404,51.56832659811781]},"properties":{"Index":7}},{"type":"Feature","geometry":{"type":"Point","coordinates":[5.02180466680957,51.55772353889625]},"properties":{"Index":8}},{"type":"Feature","geometry":{"type":"Point","coordinates":[5.03250509815485,51.5415964815148]},"properties":{"Index":9}},{"type":"Feature","geometry":{"type":"Point","coordinates":[5.03313473367888,51.54032594100156]},"properties":{"Index":10}},{"type":"Feature","geometry":{"type":"Point","coordinates":[5.03253308195592,51.53759328848199]},"properties":{"Index":11}},{"type":"Feature","geometry":{"type":"Point","coordinates":[5.03237917105004,51.53738441657148]},"properties":{"Index":12}},{"type":"Feature","geometry":{"type":"Point","coordinates":[4.99137807066502,51.50457360738875]},"properties":{"Index":13}},{"type":"Feature","geometry":{"type":"Point","coordinates":[4.97173666249458,51.48854010136759]},"properties":{"Index":14}},{"type":"Feature","geometry":{"type":"Point","coordinates":[4.9646576245199,51.48291448015738]},"properties":{"Index":15}},{"type":"Feature","geometry":{"type":"Point","coordinates":[4.96014543155817,51.47935253489351]},"properties":{"Index":16}},{"type":"Feature","geometry":{"type":"Point","coordinates":[4.95948800348742,51.47874186435425]},"properties":{"Index":17}},{"type":"Feature","geometry":{"type":"Point","coordinates":[4.94502690109517,51.46716807636804]},"properties":{"Index":18}},{"type":"Feature","geometry":{"type":"Point","coordinates":[4.94233570474112,51.465057233652]},"properties":{"Index":19}},{"type":"Feature","geometry":{"type":"Point","coordinates":[4.92920651853845,51.45406731085023]},"properties":{"Index":20}},{"type":"Feature","geometry":{"type":"Point","coordinates":[4.92754032621195,51.44315303665937]},"properties":{"Index":21}},{"type":"Feature","geometry":{"type":"Point","coordinates":[4.92899640758115,51.43034337429117]},"properties":{"Index":22}},{"type":"Feature","geometry":{"type":"Point","coordinates":[4.93179168155003,51.41221770561134]},"properties":{"Index":23}},{"type":"Feature","geometry":{"type":"Point","coordinates":[4.93186385680975,51.41178441837081]},"properties":{"Index":24}},{"type":"Feature","geometry":{"type":"Point","coordinates":[4.93299159524298,51.40524522144037]},"properties":{"Index":25}},{"type":"Feature","geometry":{"type":"Point","coordinates":[4.9337223697477,51.40114227023346]},"properties":{"Index":26}},{"type":"Feature","geometry":{"type":"Point","coordinates":[4.93360508495065,51.4007876769233]},"properties":{"Index":27}},{"type":"Feature","geometry":{"type":"Point","coordinates":[4.93402009269407,51.40144620516844]},"properties":{"Index":28}},{"type":"Feature","geometry":{"type":"Point","coordinates":[4.93421857465832,51.39705583776811]},"properties":{"Index":29}},{"type":"Feature","geometry":{"type":"Point","coordinates":[4.9380379359548,51.36989148913759]},"properties":{"Index":30}},{"type":"Feature","geometry":{"type":"Point","coordinates":[4.9380379359548,51.36989148913759]},"properties":{"Index":31}},{"type":"Feature","geometry":{"type":"Point","coordinates":[4.9431960308126,51.33523139410497]},"properties":{"Index":32}},{"type":"Feature","geometry":{"type":"Point","coordinates":[4.94310880851382,51.33290532457394]},"properties":{"Index":33}},{"type":"Feature","geometry":{"type":"Point","coordinates":[4.94294391488665,51.33178028207192]},"properties":{"Index":34}},{"type":"Feature","geometry":{"type":"Point","coordinates":[4.94378157451264,51.33155774292209]},"properties":{"Index":35}},{"type":"Feature","geometry":{"type":"Point","coordinates":[4.94157199990866,51.32992987740499]},"properties":{"Index":36}},{"type":"Feature","geometry":{"type":"Point","coordinates":[4.93819173318762,51.3219869405867]},"properties":{"Index":37}}]}