{"000":"Dit is het algemene beeld op de Petrol, dichte hekken, oude borden en slecht onderhouden industrieterrein.","001":"Oude leidingen op het industriegebied van De Petrol. Deze leidingen werden gebruikt om olie van de schepen in de haven naar de terreinen van de verschillende maatschappijen te transporteren","002":"Bovenop een van de pilaren geklommen die de pijpen ondersteunen. Hier is een platform met afsluiters.","004":"Een bunker vlakbij het rangeerterrein. Waarschijnlijk ter bewaking van het terrein.","005":"Klik op de foto voor panorama formaat"}