{"type":"FeatureCollection","features":[{"type":"Feature","geometry":{"type":"Point","coordinates":[5.65831079763343,50.75049231178329]},"properties":{"Index":0}},{"type":"Feature","geometry":{"type":"Point","coordinates":[5.65783857853136,50.75165972271517]},"properties":{"Index":1}},{"type":"Feature","geometry":{"type":"Point","coordinates":[5.65852941758809,50.75122263861951]},"properties":{"Index":2}},{"type":"Feature","geometry":{"type":"Point","coordinates":[5.65839824561529,50.75146054565877]},"properties":{"Index":3}},{"type":"Feature","geometry":{"type":"Point","coordinates":[5.65844196960622,50.7514052185482]},"properties":{"Index":4}},{"type":"Feature","geometry":{"type":"Point","coordinates":[5.6585206727899,50.75318118615473]},"properties":{"Index":5}}]}